git_repository_review/__init__.py
git_repository_review/__main__.py
git_repository_review/py.typed
git_repository_review/validate.py
git_repository_review/version.py
git_repository_review-0.1.0a0.dist-info/LICENSE
git_repository_review-0.1.0a0.dist-info/METADATA
git_repository_review-0.1.0a0.dist-info/WHEEL
git_repository_review-0.1.0a0.dist-info/RECORD
