Metadata-Version: 2.1
Name: git-repository-review
Version: 0.1.0a0
Summary: Review a Git repository to make sure it matches expected style settings and is not doing anything that is not cross-platform compatible.
Home-page: https://github.com/joelvaneenwyk/git-repository-review
License: MIT
Author: Joel Van Eenwyk
Author-email: joel.vaneenwyk@gmail.com
Requires-Python: >=3.11,<4.0
Classifier: Intended Audience :: Developers
Classifier: License :: OSI Approved :: MIT License
Classifier: Operating System :: OS Independent
Classifier: Programming Language :: Python
Classifier: Programming Language :: Python :: 3
Classifier: Programming Language :: Python :: 3.11
Classifier: Programming Language :: Python :: 3.12
Classifier: Programming Language :: Python :: 3.10
Requires-Dist: pathspec (>=0.12.1,<0.13.0)
Requires-Dist: python-dotenv (>=1.0.1,<2.0.0)
Project-URL: Bug Tracker, https://github.com/joelvaneenwyk/git-repository-review/issues
Project-URL: Changelog, https://github.com/joelvaneenwyk/git-repository-review/releases
Project-URL: Documentation, https://joelvaneenwyk.github.io/git-repository-review/
Project-URL: Repository, https://github.com/joelvaneenwyk/git-repository-review
